lib_version/__init__.py
lib_version/version.py
lib_version/version_util.py
lib_version_team17-0.1.7.dist-info/licenses/LICENSE
lib_version_team17-0.1.7.dist-info/METADATA
lib_version_team17-0.1.7.dist-info/WHEEL
lib_version_team17-0.1.7.dist-info/top_level.txt
lib_version_team17-0.1.7.dist-info/RECORD
