Metadata-Version: 2.4
Name: lib_version_team17
Version: 0.1.7
Summary: A version-aware library
Requires-Python: >=3.10
License-File: LICENSE
Dynamic: license-file
